LICENSE
MANIFEST.in
README.rst
requirements.txt
setup.py
django_socialtext.egg-info/PKG-INFO
django_socialtext.egg-info/SOURCES.txt
django_socialtext.egg-info/dependency_links.txt
django_socialtext.egg-info/requires.txt
django_socialtext.egg-info/top_level.txt
djsocialtext/__init__.py
djsocialtext/models.py
djsocialtext/signals.py
djsocialtext/test_urls.py
djsocialtext/tests.py
djsocialtext/urls.py
djsocialtext/views.py