Metadata-Version: 1.0
Name: django-socialtext
Version: 0.2.3
Summary: Django application to integrate Socialtext into your project.
Home-page: UNKNOWN
Author: Justin Murphy, The Hanover Insurance Group
Author-email: ju1murphy@hanover.com
License: UNKNOWN
Platform: UNKNOWN
Classifier: Intended Audience :: Developers
Classifier: Intended Audience :: Information Technology
Classifier: License :: OSI Approved :: Apache Software License
Classifier: Framework :: Django
Classifier: Operating System :: OS Independent
Classifier: Programming Language :: Python
